{
  "source": "d2",
  "target": "d1",
  "config": {
    "model_id": "whisper-medium",
    "target_feature_layers": "configs/extraction/audio/whisper_medium_layers.json",
    "source_tag": "d2",
    "source_data_hdf5": "outputs/neural_data/surprisal_30s.h5",
    "source_features_dir": "/work/upschrimpf1/sigfstea/multimodal-brain-scaling/outputs/features/whisper-medium-delta-t-surprisal/merged",
    "target_tag": "d1",
    "target_data_hdf5": "outputs/neural_data/broderick2018_30s.h5",
    "target_features_dir": "/work/upschrimpf1/sigfstea/multimodal-brain-scaling/outputs/features/whisper-medium-delta-t/merged",
    "output_dir": "outputs/results/whisper-medium-mtrf-xfer-pca-d2-to-d1/",
    "parcels_from": "outputs/neural_data/broderick2018_30s.h5",
    "lag_min_ms": 0.0,
    "lag_max_ms": 800.0,
    "lag_step_ms": 20.0,
    "highpass_hz": 0.5,
    "nc_threshold": 0.2,
    "n_train_time_samples": 200,
    "pca_var": 0.95,
    "use_wide_range_alphas": false,
    "layer_id": null,
    "overwrite": true,
    "seed": 42
  },
  "entries": [
    {
      "layer": "blocks.0",
      "in_domain": {
        "d2_test": [
          0.10470764338970184,
          0.11894579976797104,
          0.07064519822597504,
          0.0766444057226181
        ]
      },
      "transfer": {
        "d1_test": [
          0.0496523417532444,
          0.03543068468570709,
          0.0049125319346785545,
          0.01803603395819664
        ]
      }
    },
    {
      "layer": "blocks.1",
      "in_domain": {
        "d2_test": [
          0.14001964032649994,
          0.16643962264060974,
          0.13196852803230286,
          0.13653647899627686
        ]
      },
      "transfer": {
        "d1_test": [
          0.03960249945521355,
          0.04204840585589409,
          0.010821458883583546,
          0.012728794477880001
        ]
      }
    },
    {
      "layer": "blocks.2",
      "in_domain": {
        "d2_test": [
          0.1355217695236206,
          0.1574883759021759,
          0.12857243418693542,
          0.13164189457893372
        ]
      },
      "transfer": {
        "d1_test": [
          0.036169975996017456,
          0.02539343386888504,
          0.003986316733062267,
          0.012474446557462215
        ]
      }
    },
    {
      "layer": "blocks.3",
      "in_domain": {
        "d2_test": [
          0.13686393201351166,
          0.16333003342151642,
          0.09354940056800842,
          0.09489484131336212
        ]
      },
      "transfer": {
        "d1_test": [
          0.05672701075673103,
          0.0390312634408474,
          0.0006393506191670895,
          0.012708060443401337
        ]
      }
    },
    {
      "layer": "blocks.4",
      "in_domain": {
        "d2_test": [
          0.11758767813444138,
          0.13090147078037262,
          0.1095430999994278,
          0.11117160320281982
        ]
      },
      "transfer": {
        "d1_test": [
          0.022157039493322372,
          0.024280419573187828,
          0.0055829789489507675,
          0.013455184176564217
        ]
      }
    },
    {
      "layer": "blocks.5",
      "in_domain": {
        "d2_test": [
          0.08911412209272385,
          0.08991740643978119,
          0.048809964209795,
          0.050616417080163956
        ]
      },
      "transfer": {
        "d1_test": [
          0.024159494787454605,
          -0.0065504093654453754,
          -0.014717835001647472,
          0.0005966482567600906
        ]
      }
    },
    {
      "layer": "blocks.6",
      "in_domain": {
        "d2_test": [
          0.11116519570350647,
          0.12843719124794006,
          0.08588029444217682,
          0.08696627616882324
        ]
      },
      "transfer": {
        "d1_test": [
          0.044819749891757965,
          0.022819094359874725,
          -0.008742524310946465,
          0.002019233535975218
        ]
      }
    },
    {
      "layer": "blocks.7",
      "in_domain": {
        "d2_test": [
          0.07821982353925705,
          0.06174168735742569,
          0.043302781879901886,
          0.03996608778834343
        ]
      },
      "transfer": {
        "d1_test": [
          0.03847840800881386,
          0.00192426354624331,
          -0.0026963315904140472,
          0.017287906259298325
        ]
      }
    },
    {
      "layer": "blocks.8",
      "in_domain": {
        "d2_test": [
          0.07570527493953705,
          0.07701447606086731,
          0.040971215814352036,
          0.03536572679877281
        ]
      },
      "transfer": {
        "d1_test": [
          0.037112656980752945,
          0.019920019432902336,
          -0.000641531718429178,
          0.011012623086571693
        ]
      }
    },
    {
      "layer": "blocks.9",
      "in_domain": {
        "d2_test": [
          0.1054060310125351,
          0.13080836832523346,
          0.07439704239368439,
          0.07827481627464294
        ]
      },
      "transfer": {
        "d1_test": [
          0.04741223156452179,
          0.032110270112752914,
          0.007532666902989149,
          0.020190302282571793
        ]
      }
    },
    {
      "layer": "blocks.10",
      "in_domain": {
        "d2_test": [
          0.1531648337841034,
          0.17484407126903534,
          0.11539915204048157,
          0.11760977655649185
        ]
      },
      "transfer": {
        "d1_test": [
          0.049695469439029694,
          0.040575411170721054,
          0.015163534320890903,
          0.016516242176294327
        ]
      }
    },
    {
      "layer": "blocks.11",
      "in_domain": {
        "d2_test": [
          0.12174087762832642,
          0.1484510749578476,
          0.09937635809183121,
          0.10457055270671844
        ]
      },
      "transfer": {
        "d1_test": [
          0.03817056119441986,
          0.013084189034998417,
          0.005620723124593496,
          0.009799734689295292
        ]
      }
    },
    {
      "layer": "blocks.12",
      "in_domain": {
        "d2_test": [
          0.13482874631881714,
          0.1695646345615387,
          0.10242341458797455,
          0.10515298694372177
        ]
      },
      "transfer": {
        "d1_test": [
          0.07050223648548126,
          0.038750916719436646,
          -0.0028076660819351673,
          0.005402720998972654
        ]
      }
    },
    {
      "layer": "blocks.13",
      "in_domain": {
        "d2_test": [
          0.12203044444322586,
          0.1320597231388092,
          0.08501827716827393,
          0.07983600348234177
        ]
      },
      "transfer": {
        "d1_test": [
          0.053917642682790756,
          0.043119609355926514,
          0.0004526884004008025,
          0.008708711713552475
        ]
      }
    },
    {
      "layer": "blocks.14",
      "in_domain": {
        "d2_test": [
          0.1532059907913208,
          0.19201438128948212,
          0.11198459565639496,
          0.11789561808109283
        ]
      },
      "transfer": {
        "d1_test": [
          0.06356453895568848,
          0.04138804227113724,
          0.00471365824341774,
          0.01215533446520567
        ]
      }
    },
    {
      "layer": "blocks.15",
      "in_domain": {
        "d2_test": [
          0.1582353711128235,
          0.1977073699235916,
          0.11360343545675278,
          0.12006145715713501
        ]
      },
      "transfer": {
        "d1_test": [
          0.06640899926424026,
          0.0507456511259079,
          0.005859280005097389,
          0.007615098729729652
        ]
      }
    },
    {
      "layer": "blocks.16",
      "in_domain": {
        "d2_test": [
          0.13783253729343414,
          0.17753514647483826,
          0.11033201962709427,
          0.11524976044893265
        ]
      },
      "transfer": {
        "d1_test": [
          0.06522917002439499,
          0.057526711374521255,
          0.00919186882674694,
          0.016041535884141922
        ]
      }
    },
    {
      "layer": "blocks.17",
      "in_domain": {
        "d2_test": [
          0.10324669629335403,
          0.14490586519241333,
          0.08640827238559723,
          0.09274323284626007
        ]
      },
      "transfer": {
        "d1_test": [
          0.05405248701572418,
          0.046945054084062576,
          -0.003103525610640645,
          0.007326382212340832
        ]
      }
    },
    {
      "layer": "blocks.18",
      "in_domain": {
        "d2_test": [
          0.12344785779714584,
          0.16704830527305603,
          0.08619917929172516,
          0.09018231183290482
        ]
      },
      "transfer": {
        "d1_test": [
          0.06014476716518402,
          0.0470009371638298,
          0.011518153361976147,
          0.020539995282888412
        ]
      }
    },
    {
      "layer": "blocks.19",
      "in_domain": {
        "d2_test": [
          0.16963805258274078,
          0.2133384346961975,
          0.13162775337696075,
          0.13892214000225067
        ]
      },
      "transfer": {
        "d1_test": [
          0.060611478984355927,
          0.04781268909573555,
          0.008461306802928448,
          0.012623020447790623
        ]
      }
    },
    {
      "layer": "blocks.20",
      "in_domain": {
        "d2_test": [
          0.14611448347568512,
          0.19903302192687988,
          0.10911761224269867,
          0.1186245009303093
        ]
      },
      "transfer": {
        "d1_test": [
          0.06980551779270172,
          0.05664794519543648,
          0.005387742538005114,
          0.013970705680549145
        ]
      }
    }
  ]
}